[
  {
    "dbHeader": "meta",
    "dbRelation": "subject",
    "dbType": "json",
    "dbClass": "ObjectOrientedDatabase",
    "objectClass": "hideall"
  },
  

  {"objectName": "<i class='fa-solid fa-angles-right fax-col2'></i>&nbsp; Class 11 &nbsp;<i class='fa-solid fa-angles-left fax-col1'></i>",
    "anchorClass": "inactiveClassA",
    "liClass": "divider"},
  
  { "id": 1, "objectName": "সরল অণুবীক্ষণযন্ত্র অধ্যয়ন", "objectUrl": "hscbio01.pdf" },
  { "id": 2, "objectName": "যৌগিক অণুবীক্ষণযন্ত্র অধ্যয়ন", "objectUrl": "hscbio02.pdf" },
  { "id": 3, "objectName": "মাইটোসিসের বিভিন্ন পর্যায় পর্যবেক্ষণ", "objectUrl": "hscbio03.pdf" },
  { "id": 4, "objectName": "টক দই থেকে ব্যাকটেরিয়া পর্যবেক্ষণ", "objectUrl": "hscbio04.pdf" },
  
  
  {
    "dbFooter": "meta",
    "dbScripts": "/index.js",
    "dbVersion": "stable",
    "objectClass": "hideall"
  }
]
